{
	"name": "ORA_SAP_IN_ONLINEMALL_D",
	"properties": {
		"activities": [
			{
				"name": "PIP_M_CD_MART_DM_CM_BO_SAPITEM_MAPPING_T_FULL",
				"type": "ExecutePipeline",
				"dependsOn": [
					{
						"activity": "Input log",
						"dependencyConditions": [
							"Succeeded"
						]
					}
				],
				"policy": {
					"secureInput": false
				},
				"userProperties": [],
				"typeProperties": {
					"pipeline": {
						"referenceName": "PIP_M_CD_MART_DM_CM_BO_SAPITEM_MAPPING_T_FULL",
						"type": "PipelineReference"
					},
					"waitOnCompletion": true
				}
			},
			{
				"name": "PIP_M_CD_MART_DM_CM_JW_SAPITEM_MAPPING_T_FULL",
				"type": "ExecutePipeline",
				"dependsOn": [
					{
						"activity": "Input log 2",
						"dependencyConditions": [
							"Succeeded"
						]
					}
				],
				"policy": {
					"secureInput": false
				},
				"userProperties": [],
				"typeProperties": {
					"pipeline": {
						"referenceName": "PIP_M_CD_MART_DM_CM_JW_SAPITEM_MAPPING_T_FULL",
						"type": "PipelineReference"
					},
					"waitOnCompletion": true
				}
			},
			{
				"name": "Input log",
				"type": "Lookup",
				"dependsOn": [],
				"policy": {
					"timeout": "0.12:00:00",
					"retry": 0,
					"retryIntervalInSeconds": 30,
					"secureOutput": false,
					"secureInput": false
				},
				"userProperties": [],
				"typeProperties": {
					"source": {
						"type": "OracleSource",
						"oracleReaderQuery": {
							"value": "select CD_IF.FUNC_CDI_LOG(  'I' , p_pipline => 'PIP_M_CD_MART_DM_CM_BO_SAPITEM_MAPPING_T_FULL' ) as result from dual",
							"type": "Expression"
						},
						"partitionOption": "None",
						"convertDecimalToInteger": false,
						"queryTimeout": "02:00:00"
					},
					"dataset": {
						"referenceName": "DTS_ORACLE_SRC",
						"type": "DatasetReference",
						"parameters": {
							"SourceSchema": "1",
							"SourceTable": "1"
						}
					}
				}
			},
			{
				"name": "Input log 2",
				"type": "Lookup",
				"dependsOn": [],
				"policy": {
					"timeout": "0.12:00:00",
					"retry": 0,
					"retryIntervalInSeconds": 30,
					"secureOutput": false,
					"secureInput": false
				},
				"userProperties": [],
				"typeProperties": {
					"source": {
						"type": "OracleSource",
						"oracleReaderQuery": {
							"value": "select CD_IF.FUNC_CDI_LOG(  'I' , p_pipline => 'PIP_M_CD_MART_DM_CM_JW_SAPITEM_MAPPING_T_FULL' ) as result from dual",
							"type": "Expression"
						},
						"partitionOption": "None",
						"convertDecimalToInteger": false,
						"queryTimeout": "02:00:00"
					},
					"dataset": {
						"referenceName": "DTS_ORACLE_SRC",
						"type": "DatasetReference",
						"parameters": {
							"SourceSchema": "1",
							"SourceTable": "1"
						}
					}
				}
			},
			{
				"name": "Output Success log",
				"type": "Lookup",
				"dependsOn": [
					{
						"activity": "PIP_M_CD_MART_DM_CM_BO_SAPITEM_MAPPING_T_FULL",
						"dependencyConditions": [
							"Succeeded"
						]
					}
				],
				"policy": {
					"timeout": "0.12:00:00",
					"retry": 0,
					"retryIntervalInSeconds": 30,
					"secureOutput": false,
					"secureInput": false
				},
				"userProperties": [],
				"typeProperties": {
					"source": {
						"type": "OracleSource",
						"oracleReaderQuery": {
							"value": "@concat('select CD_IF.FUNC_CDI_LOG(''U'' , p_seq => ''', activity('Input log').output.firstRow.RESULT, ''', p_result => ''S'') as result from dual')",
							"type": "Expression"
						},
						"partitionOption": "None",
						"convertDecimalToInteger": false,
						"queryTimeout": "02:00:00"
					},
					"dataset": {
						"referenceName": "DTS_ORACLE_SRC",
						"type": "DatasetReference",
						"parameters": {
							"SourceSchema": "1",
							"SourceTable": "1"
						}
					}
				}
			},
			{
				"name": "Output Error log",
				"type": "Lookup",
				"dependsOn": [
					{
						"activity": "PIP_M_CD_MART_DM_CM_BO_SAPITEM_MAPPING_T_FULL",
						"dependencyConditions": [
							"Failed"
						]
					}
				],
				"policy": {
					"timeout": "0.12:00:00",
					"retry": 0,
					"retryIntervalInSeconds": 30,
					"secureOutput": false,
					"secureInput": false
				},
				"userProperties": [],
				"typeProperties": {
					"source": {
						"type": "OracleSource",
						"oracleReaderQuery": {
							"value": "@concat('select CD_IF.FUNC_CDI_LOG(''U'' , p_seq => ''', activity('Input log').output.firstRow.RESULT, ''', p_result => ''E'', p_error_msg => ''', replace(activity('PIP_M_CD_MART_DM_CM_BO_SAPITEM_MAPPING_T_FULL').Error.Message, '''','‘'),''') as result from dual')",
							"type": "Expression"
						},
						"partitionOption": "None",
						"convertDecimalToInteger": false,
						"queryTimeout": "02:00:00"
					},
					"dataset": {
						"referenceName": "DTS_ORACLE_SRC",
						"type": "DatasetReference",
						"parameters": {
							"SourceSchema": "1",
							"SourceTable": "1"
						}
					}
				}
			},
			{
				"name": "Output Success log 2",
				"type": "Lookup",
				"dependsOn": [
					{
						"activity": "PIP_M_CD_MART_DM_CM_JW_SAPITEM_MAPPING_T_FULL",
						"dependencyConditions": [
							"Succeeded"
						]
					}
				],
				"policy": {
					"timeout": "0.12:00:00",
					"retry": 0,
					"retryIntervalInSeconds": 30,
					"secureOutput": false,
					"secureInput": false
				},
				"userProperties": [],
				"typeProperties": {
					"source": {
						"type": "OracleSource",
						"oracleReaderQuery": {
							"value": "@concat('select CD_IF.FUNC_CDI_LOG(''U'' , p_seq => ''', activity('Input log 2').output.firstRow.RESULT, ''', p_result => ''S'') as result from dual')",
							"type": "Expression"
						},
						"partitionOption": "None",
						"convertDecimalToInteger": false,
						"queryTimeout": "02:00:00"
					},
					"dataset": {
						"referenceName": "DTS_ORACLE_SRC",
						"type": "DatasetReference",
						"parameters": {
							"SourceSchema": "1",
							"SourceTable": "1"
						}
					}
				}
			},
			{
				"name": "Output Error log 2",
				"type": "Lookup",
				"dependsOn": [
					{
						"activity": "PIP_M_CD_MART_DM_CM_JW_SAPITEM_MAPPING_T_FULL",
						"dependencyConditions": [
							"Failed"
						]
					}
				],
				"policy": {
					"timeout": "0.12:00:00",
					"retry": 0,
					"retryIntervalInSeconds": 30,
					"secureOutput": false,
					"secureInput": false
				},
				"userProperties": [],
				"typeProperties": {
					"source": {
						"type": "OracleSource",
						"oracleReaderQuery": {
							"value": "@concat('select CD_IF.FUNC_CDI_LOG(''U'' , p_seq => ''', activity('Input log 2').output.firstRow.RESULT, ''', p_result => ''E'', p_error_msg => ''', replace(activity('PIP_M_CD_MART_DM_CM_JW_SAPITEM_MAPPING_T_FULL').Error.Message, '''','‘'),''') as result from dual')",
							"type": "Expression"
						},
						"partitionOption": "None",
						"convertDecimalToInteger": false,
						"queryTimeout": "02:00:00"
					},
					"dataset": {
						"referenceName": "DTS_ORACLE_SRC",
						"type": "DatasetReference",
						"parameters": {
							"SourceSchema": "1",
							"SourceTable": "1"
						}
					}
				}
			}
		],
		"folder": {
			"name": "실행/Daily"
		},
		"annotations": [],
		"lastPublishTime": "2023-01-17T01:13:11Z"
	},
	"type": "Microsoft.DataFactory/factories/pipelines"
}