{
	"name": "PIP_D_CD_NEIS_BID_MASTER_FULL_PG_SCHOOL",
	"properties": {
		"activities": [
			{
				"name": "Copy data",
				"type": "Copy",
				"dependsOn": [],
				"policy": {
					"timeout": "7.00:00:00",
					"retry": 0,
					"retryIntervalInSeconds": 30,
					"secureOutput": false,
					"secureInput": false
				},
				"userProperties": [],
				"typeProperties": {
					"source": {
						"type": "OracleSource",
						"oracleReaderQuery": "SELECT * FROM CD_NEIS.BID_MASTER\nWHERE orgtype = 'S'",
						"partitionOption": "None",
						"queryTimeout": "02:00:00"
					},
					"sink": {
						"type": "AzurePostgreSQLSink",
						"writeBatchSize": 1000000,
						"writeBatchTimeout": "00:30:00",
						"preCopyScript": {
							"value": "DELETE FROM @{pipeline().parameters.SinkSchema}.@{pipeline().parameters.SinkTable}",
							"type": "Expression"
						},
						"writeMethod": "CopyCommand"
					},
					"enableStaging": false,
					"translator": {
						"type": "TabularTranslator",
						"mappings": [
							{
								"source": {
									"name": "DOCID",
									"type": "String"
								},
								"sink": {
									"name": "docid",
									"type": "String",
									"physicalType": "character varying"
								}
							},
							{
								"source": {
									"name": "BIDID",
									"type": "String"
								},
								"sink": {
									"name": "bidid",
									"type": "String",
									"physicalType": "character varying"
								}
							},
							{
								"source": {
									"name": "SUBJECT",
									"type": "String"
								},
								"sink": {
									"name": "subject",
									"type": "String",
									"physicalType": "character varying"
								}
							},
							{
								"source": {
									"name": "POSTDATE",
									"type": "DateTime"
								},
								"sink": {
									"name": "postdate",
									"type": "DateTime",
									"physicalType": "timestamp without time zone"
								}
							},
							{
								"source": {
									"name": "START_DT",
									"type": "DateTime"
								},
								"sink": {
									"name": "start_dt",
									"type": "DateTime",
									"physicalType": "timestamp without time zone"
								}
							},
							{
								"source": {
									"name": "END_DT",
									"type": "DateTime"
								},
								"sink": {
									"name": "end_dt",
									"type": "DateTime",
									"physicalType": "timestamp without time zone"
								}
							},
							{
								"source": {
									"name": "STATUS",
									"type": "String"
								},
								"sink": {
									"name": "status",
									"type": "String",
									"physicalType": "character varying"
								}
							},
							{
								"source": {
									"name": "ORGNAME",
									"type": "String"
								},
								"sink": {
									"name": "orgname",
									"type": "String",
									"physicalType": "character varying"
								}
							},
							{
								"source": {
									"name": "ORG_BIZ_ID",
									"type": "String"
								},
								"sink": {
									"name": "org_biz_id",
									"type": "String",
									"physicalType": "character varying"
								}
							},
							{
								"source": {
									"name": "AGENCY",
									"type": "String"
								},
								"sink": {
									"name": "agency",
									"type": "String",
									"physicalType": "character varying"
								}
							},
							{
								"source": {
									"name": "AMOUNT",
									"type": "Double"
								},
								"sink": {
									"name": "amount",
									"type": "Decimal",
									"physicalType": "numeric"
								}
							},
							{
								"source": {
									"name": "KWD",
									"type": "String"
								},
								"sink": {
									"name": "kwd",
									"type": "String",
									"physicalType": "character varying"
								}
							},
							{
								"source": {
									"name": "WORK_DT",
									"type": "DateTime"
								},
								"sink": {
									"name": "work_dt",
									"type": "DateTime",
									"physicalType": "timestamp without time zone"
								}
							},
							{
								"source": {
									"name": "SAP_ID",
									"type": "String"
								},
								"sink": {
									"name": "sap_id",
									"type": "String",
									"physicalType": "character varying"
								}
							},
							{
								"source": {
									"name": "SAP_NM",
									"type": "String"
								},
								"sink": {
									"name": "sap_nm",
									"type": "String",
									"physicalType": "character varying"
								}
							},
							{
								"source": {
									"name": "CREATE_ID",
									"type": "String"
								},
								"sink": {
									"name": "create_id",
									"type": "String",
									"physicalType": "character varying"
								}
							},
							{
								"source": {
									"name": "CREATE_DT",
									"type": "DateTime"
								},
								"sink": {
									"name": "create_dt",
									"type": "DateTime",
									"physicalType": "timestamp without time zone"
								}
							},
							{
								"source": {
									"name": "UPDATE_ID",
									"type": "String"
								},
								"sink": {
									"name": "update_id",
									"type": "String",
									"physicalType": "character varying"
								}
							},
							{
								"source": {
									"name": "UPDATE_DT",
									"type": "DateTime"
								},
								"sink": {
									"name": "update_dt",
									"type": "DateTime",
									"physicalType": "timestamp without time zone"
								}
							},
							{
								"source": {
									"name": "USE_YN",
									"type": "String"
								},
								"sink": {
									"name": "use_yn",
									"type": "String",
									"physicalType": "character varying"
								}
							},
							{
								"source": {
									"name": "KWD_CHK_ID",
									"type": "String"
								},
								"sink": {
									"name": "kwd_chk_id",
									"type": "String",
									"physicalType": "character varying"
								}
							},
							{
								"source": {
									"name": "KWD_CHK_DATE",
									"type": "DateTime"
								},
								"sink": {
									"name": "kwd_chk_date",
									"type": "DateTime",
									"physicalType": "timestamp without time zone"
								}
							},
							{
								"source": {
									"name": "AGENCY_UPDATE_ID",
									"type": "String"
								},
								"sink": {
									"name": "agency_update_id",
									"type": "String",
									"physicalType": "character varying"
								}
							},
							{
								"source": {
									"name": "AGENCY_UPDATE_DT",
									"type": "DateTime"
								},
								"sink": {
									"name": "agency_update_dt",
									"type": "DateTime",
									"physicalType": "timestamp without time zone"
								}
							},
							{
								"source": {
									"name": "START_AMOUNT",
									"type": "Double"
								},
								"sink": {
									"name": "start_amount",
									"type": "Decimal",
									"physicalType": "numeric"
								}
							},
							{
								"source": {
									"name": "AGENCY_BIZ_ID",
									"type": "String"
								},
								"sink": {
									"name": "agency_biz_id",
									"type": "String",
									"physicalType": "character varying"
								}
							},
							{
								"source": {
									"name": "TENDER_RATE",
									"type": "Double"
								},
								"sink": {
									"name": "tender_rate",
									"type": "Decimal",
									"physicalType": "numeric"
								}
							}
						],
						"typeConversion": true,
						"typeConversionSettings": {
							"allowDataTruncation": true,
							"treatBooleanAsNumber": false
						}
					}
				},
				"inputs": [
					{
						"referenceName": "DTS_ORACLE_SRC",
						"type": "DatasetReference",
						"parameters": {
							"SourceSchema": {
								"value": "@pipeline().parameters.SourceSchema",
								"type": "Expression"
							},
							"SourceTable": {
								"value": "@pipeline().parameters.SourceTable",
								"type": "Expression"
							}
						}
					}
				],
				"outputs": [
					{
						"referenceName": "DTS_POSTGRESQL_SNK_P02",
						"type": "DatasetReference",
						"parameters": {
							"SinkSchema": {
								"value": "@pipeline().parameters.SinkSchema",
								"type": "Expression"
							},
							"SinkTable": {
								"value": "@pipeline().parameters.SinkTable",
								"type": "Expression"
							}
						}
					}
				]
			}
		],
		"parameters": {
			"SourceSchema": {
				"type": "string",
				"defaultValue": "CD_NEIS"
			},
			"SourceTable": {
				"type": "string",
				"defaultValue": "BID_MASTER"
			},
			"SinkSchema": {
				"type": "string",
				"defaultValue": "cd_ods"
			},
			"SinkTable": {
				"type": "string",
				"defaultValue": "tb_sf_eat_bid_master"
			}
		},
		"folder": {
			"name": "판촉/내부/급식입개찰"
		},
		"annotations": [],
		"lastPublishTime": "2022-10-18T08:30:36Z"
	},
	"type": "Microsoft.DataFactory/factories/pipelines"
}