{
	"name": "PIP_PG_AZURE_LICENSE_LOG",
	"properties": {
		"activities": [
			{
				"name": "Copy_User",
				"type": "Copy",
				"dependsOn": [
					{
						"activity": "Set Date",
						"dependencyConditions": [
							"Succeeded"
						]
					}
				],
				"policy": {
					"timeout": "0.12:00:00",
					"retry": 0,
					"retryIntervalInSeconds": 30,
					"secureOutput": false,
					"secureInput": false
				},
				"userProperties": [],
				"typeProperties": {
					"source": {
						"type": "RestSource",
						"additionalColumns": [
							{
								"name": "date",
								"value": {
									"value": "@variables('p_snapshot_date')",
									"type": "Expression"
								}
							}
						],
						"httpRequestTimeout": "00:01:40",
						"requestInterval": "00.00:00:00.010",
						"requestMethod": "GET",
						"paginationRules": {
							"AbsoluteUrl": {
								"value": "$['@odata.nextLink']",
								"type": "Expression"
							}
						}
					},
					"sink": {
						"type": "AzurePostgreSqlSink",
						"writeBatchSize": 1000000,
						"writeBatchTimeout": "00:30:00",
						"writeMethod": "CopyCommand"
					},
					"enableStaging": false,
					"translator": {
						"type": "TabularTranslator",
						"mappings": [
							{
								"source": {
									"path": "['id']"
								},
								"sink": {
									"name": "user_id",
									"type": "String"
								}
							},
							{
								"source": {
									"path": "['displayName']"
								},
								"sink": {
									"name": "display_name",
									"type": "String"
								}
							},
							{
								"source": {
									"path": "['givenName']"
								},
								"sink": {
									"name": "given_name",
									"type": "String"
								}
							},
							{
								"source": {
									"path": "['surname']"
								},
								"sink": {
									"name": "surname",
									"type": "String"
								}
							},
							{
								"source": {
									"path": "['userPrincipalName']"
								},
								"sink": {
									"name": "user_principal_name",
									"type": "String"
								}
							},
							{
								"source": {
									"path": "['companyName']"
								},
								"sink": {
									"name": "company_name",
									"type": "String"
								}
							},
							{
								"source": {
									"path": "['employeeId']"
								},
								"sink": {
									"name": "employee_id",
									"type": "String"
								}
							},
							{
								"source": {
									"path": "$['date']"
								},
								"sink": {
									"name": "snapshot_date",
									"type": "DateTime"
								}
							}
						],
						"collectionReference": "$['value']",
						"mapComplexValuesToString": false
					}
				},
				"inputs": [
					{
						"referenceName": "AZURE_USER_INFO",
						"type": "DatasetReference",
						"parameters": {
							"url": "/v1.0/users?$select=id,displayName,givenName,surname,userPrincipalName,companyName,employeeId"
						}
					}
				],
				"outputs": [
					{
						"referenceName": "DTS_POSTGRESQL_SNK",
						"type": "DatasetReference",
						"parameters": {
							"SinkSchema": "cd_ods",
							"SinkTable": "tb_azure_user_info"
						}
					}
				]
			},
			{
				"name": "Set Date",
				"type": "SetVariable",
				"dependsOn": [],
				"policy": {
					"secureOutput": false,
					"secureInput": false
				},
				"userProperties": [],
				"typeProperties": {
					"variableName": "p_snapshot_date",
					"value": {
						"value": "@formatDateTime(utcNow(),'yyyy-MM-dd')",
						"type": "Expression"
					}
				}
			},
			{
				"name": "Copy_Group",
				"type": "Copy",
				"dependsOn": [
					{
						"activity": "Set Date",
						"dependencyConditions": [
							"Succeeded"
						]
					}
				],
				"policy": {
					"timeout": "0.12:00:00",
					"retry": 0,
					"retryIntervalInSeconds": 30,
					"secureOutput": false,
					"secureInput": false
				},
				"userProperties": [],
				"typeProperties": {
					"source": {
						"type": "RestSource",
						"additionalColumns": [
							{
								"name": "date",
								"value": {
									"value": "@variables('p_snapshot_date')",
									"type": "Expression"
								}
							}
						],
						"httpRequestTimeout": "00:01:40",
						"requestInterval": "00.00:00:00.010",
						"requestMethod": "GET",
						"paginationRules": {
							"AbsoluteUrl": {
								"value": "$['@odata.nextLink']",
								"type": "Expression"
							}
						}
					},
					"sink": {
						"type": "AzurePostgreSqlSink",
						"writeBatchSize": 1000000,
						"writeBatchTimeout": "00:30:00",
						"writeMethod": "CopyCommand"
					},
					"enableStaging": false,
					"translator": {
						"type": "TabularTranslator",
						"mappings": [
							{
								"source": {
									"path": "['id']"
								},
								"sink": {
									"name": "group_id",
									"type": "String"
								}
							},
							{
								"source": {
									"path": "['displayName']"
								},
								"sink": {
									"name": "group_name",
									"type": "String"
								}
							},
							{
								"source": {
									"path": "$['date']"
								},
								"sink": {
									"name": "snapshot_date",
									"type": "DateTime"
								}
							}
						],
						"collectionReference": "$['value']",
						"mapComplexValuesToString": false
					}
				},
				"inputs": [
					{
						"referenceName": "AZURE_USER_INFO",
						"type": "DatasetReference",
						"parameters": {
							"url": "/v1.0/groups?$select=id,displayName&$top=100"
						}
					}
				],
				"outputs": [
					{
						"referenceName": "DTS_POSTGRESQL_SNK",
						"type": "DatasetReference",
						"parameters": {
							"SinkSchema": "cd_ods",
							"SinkTable": "tb_azure_group_info"
						}
					}
				]
			},
			{
				"name": "Lookup_",
				"type": "Lookup",
				"dependsOn": [
					{
						"activity": "Copy_Group",
						"dependencyConditions": [
							"Succeeded"
						]
					}
				],
				"policy": {
					"timeout": "0.12:00:00",
					"retry": 0,
					"retryIntervalInSeconds": 30,
					"secureOutput": false,
					"secureInput": false
				},
				"userProperties": [],
				"typeProperties": {
					"source": {
						"type": "AzurePostgreSqlSource",
						"query": "select distinct group_id from cd_ods.tb_azure_group_info\nwhere snapshot_date =CURRENT_DATE",
						"partitionOption": "None",
						"queryTimeout": "02:00:00"
					},
					"dataset": {
						"referenceName": "DTS_POSTGRESQL_SNK",
						"type": "DatasetReference",
						"parameters": {
							"SinkSchema": "1",
							"SinkTable": "1"
						}
					},
					"firstRowOnly": false
				}
			},
			{
				"name": "ForEach1",
				"type": "ForEach",
				"dependsOn": [
					{
						"activity": "Lookup_",
						"dependencyConditions": [
							"Succeeded"
						]
					}
				],
				"userProperties": [],
				"typeProperties": {
					"items": {
						"value": "@activity('Lookup_').output.value",
						"type": "Expression"
					},
					"isSequential": true,
					"activities": [
						{
							"name": "Copy data1",
							"type": "Copy",
							"dependsOn": [],
							"policy": {
								"timeout": "0.12:00:00",
								"retry": 0,
								"retryIntervalInSeconds": 30,
								"secureOutput": false,
								"secureInput": false
							},
							"userProperties": [],
							"typeProperties": {
								"source": {
									"type": "RestSource",
									"additionalColumns": [
										{
											"name": "date",
											"value": {
												"value": "@variables('p_snapshot_date')",
												"type": "Expression"
											}
										},
										{
											"name": "Group_id",
											"value": {
												"value": "@item().group_id",
												"type": "Expression"
											}
										}
									],
									"httpRequestTimeout": "00:01:40",
									"requestInterval": "00.00:00:00.010",
									"requestMethod": "GET",
									"paginationRules": {
										"AbsoluteUrl": {
											"value": "$['@odata.nextLink']",
											"type": "Expression"
										}
									}
								},
								"sink": {
									"type": "AzurePostgreSqlSink",
									"writeBatchSize": 1000000,
									"writeBatchTimeout": "00:30:00",
									"writeMethod": "CopyCommand"
								},
								"enableStaging": false,
								"translator": {
									"type": "TabularTranslator",
									"mappings": [
										{
											"source": {
												"path": "['id']"
											},
											"sink": {
												"name": "user_id",
												"type": "String"
											}
										},
										{
											"source": {
												"path": "$['date']"
											},
											"sink": {
												"name": "snapshot_date",
												"type": "DateTime"
											}
										},
										{
											"source": {
												"path": "$['Group_id']"
											},
											"sink": {
												"name": "group_id",
												"type": "String"
											}
										}
									],
									"collectionReference": "$['value']"
								}
							},
							"inputs": [
								{
									"referenceName": "AZURE_USER_INFO",
									"type": "DatasetReference",
									"parameters": {
										"url": {
											"value": "/v1.0/groups/@{item().group_id}/transitiveMembers/microsoft.graph.user?$select=id,userPrincipalName,displayName&$top=999\n",
											"type": "Expression"
										}
									}
								}
							],
							"outputs": [
								{
									"referenceName": "DTS_POSTGRESQL_SNK",
									"type": "DatasetReference",
									"parameters": {
										"SinkSchema": "cd_ods",
										"SinkTable": "tb_azure_group_user_mapping"
									}
								}
							]
						}
					]
				}
			}
		],
		"variables": {
			"p_snapshot_date": {
				"type": "String"
			}
		},
		"folder": {
			"name": "사용자/내부"
		},
		"annotations": []
	}
}