{
	"name": "PIP_API_INDUSTRY_BULESIS_BRAND_INFO",
	"properties": {
		"activities": [
			{
				"name": "Copy data_brand_master",
				"type": "Copy",
				"dependsOn": [],
				"policy": {
					"timeout": "0.12:00:00",
					"retry": 0,
					"retryIntervalInSeconds": 30,
					"secureOutput": false,
					"secureInput": false
				},
				"userProperties": [],
				"typeProperties": {
					"source": {
						"type": "JsonSource",
						"storeSettings": {
							"type": "HttpReadSettings",
							"requestMethod": "GET"
						},
						"formatSettings": {
							"type": "JsonReadSettings"
						}
					},
					"sink": {
						"type": "AzurePostgreSqlSink",
						"writeBatchSize": 1000000,
						"writeBatchTimeout": "00:30:00",
						"writeMethod": "CopyCommand"
					},
					"enableStaging": false,
					"translator": {
						"type": "TabularTranslator",
						"mappings": [
							{
								"source": {
									"path": "['br_code']"
								},
								"sink": {
									"name": "br_code",
									"type": "String"
								}
							},
							{
								"source": {
									"path": "['brname']"
								},
								"sink": {
									"name": "brname",
									"type": "String"
								}
							},
							{
								"source": {
									"path": "['area']"
								},
								"sink": {
									"name": "area",
									"type": "String"
								}
							}
						],
						"collectionReference": "$['data']"
					}
				},
				"inputs": [
					{
						"referenceName": "DTS_API_BLUESIS",
						"type": "DatasetReference",
						"parameters": {
							"url": {
								"value": "@concat('/api/brands?key=XNBGd1SDc9OLQQEFNuowuBcFwj62JY30')",
								"type": "Expression"
							}
						}
					}
				],
				"outputs": [
					{
						"referenceName": "DTS_POSTGRESQL_SNK_P02",
						"type": "DatasetReference",
						"parameters": {
							"SinkSchema": "@pipeline().parameters.SinkSchema",
							"SinkTable": {
								"value": "@pipeline().parameters.SinkTable",
								"type": "Expression"
							}
						}
					}
				]
			}
		],
		"parameters": {
			"SinkSchema": {
				"type": "string",
				"defaultValue": "cd_ods"
			},
			"SinkTable": {
				"type": "string",
				"defaultValue": "tb_sf_bluesis_brand_info_t"
			}
		},
		"folder": {
			"name": "Industry/외부/블루시스"
		},
		"annotations": []
	}
}